referer/__init__.py
referer/context_processors.py
referer/settings.py
referer/middleware/__init__.py
referer/middleware/referer.py
django_referer-0.1.0.dist-info/LICENSE.txt
django_referer-0.1.0.dist-info/METADATA
django_referer-0.1.0.dist-info/WHEEL
django_referer-0.1.0.dist-info/top_level.txt
django_referer-0.1.0.dist-info/RECORD
