Metadata-Version: 2.1
Name: django-referer
Version: 0.1.0
Summary: Keep HTTP referer information on query parameter and display referer information
Home-page: https://github.com/yifaneye/django-referer
Author: Yifan Ai
Author-email: yifanai@aol.com
License: UNKNOWN
Platform: UNKNOWN
Classifier: Programming Language :: Python :: 3
Classifier: License :: OSI Approved :: MIT License
Classifier: Operating System :: OS Independent
Requires-Dist: Django
Requires-Dist: furl
